server_extension/__init__.py
server_extension/_version.py
server_extension/handlers.py
server_extension/labextension/package.json
server_extension/labextension/static/509.ac566ece64c55de8b561.js
server_extension/labextension/static/631.e720c98242b895ba90d8.js
server_extension/labextension/static/remoteEntry.eea88a09a3663a75e547.js
server_extension/labextension/static/style.js
server_extension/labextension/static/third-party-licenses.json
server_extension/tests/__init__.py
server_extension/tests/test_handlers.py
server_extension-0.1.3.data/data/etc/jupyter/jupyter_server_config.d/server_extension.json
server_extension-0.1.3.data/data/share/jupyter/labextensions/server-extension/package.json
server_extension-0.1.3.data/data/share/jupyter/labextensions/server-extension/static/509.ac566ece64c55de8b561.js
server_extension-0.1.3.data/data/share/jupyter/labextensions/server-extension/static/631.e720c98242b895ba90d8.js
server_extension-0.1.3.data/data/share/jupyter/labextensions/server-extension/static/remoteEntry.eea88a09a3663a75e547.js
server_extension-0.1.3.data/data/share/jupyter/labextensions/server-extension/static/style.js
server_extension-0.1.3.data/data/share/jupyter/labextensions/server-extension/static/third-party-licenses.json
server_extension-0.1.3.data/data/share/jupyter/labextensions/server-extension/install.json
server_extension-0.1.3.dist-info/METADATA
server_extension-0.1.3.dist-info/WHEEL
server_extension-0.1.3.dist-info/licenses/LICENSE
server_extension-0.1.3.dist-info/RECORD
